settlesdk/__init__.py
settlesdk-0.0.7.dist-info/LICENSE
settlesdk-0.0.7.dist-info/METADATA
settlesdk-0.0.7.dist-info/WHEEL
settlesdk-0.0.7.dist-info/top_level.txt
settlesdk-0.0.7.dist-info/RECORD
