Metadata-Version: 2.1
Name: settlesdk
Version: 0.0.7
Summary: The Settle SDK abstracts using the price feed and settle API by wrapping authentication in a function.
Home-page: https://github.com/SettleFinance/Settle-SDK-Python
Author: Adam Peretti
Author-email: adam.peretti@gmail.com
License: UNKNOWN
Platform: UNKNOWN
Classifier: Programming Language :: Python :: 3
Classifier: License :: OSI Approved :: MIT License
Classifier: Operating System :: OS Independent
Requires-Dist: PyJWT
Requires-Dist: python-dotenv
Requires-Dist: requests
Requires-Dist: cryptography
